nornir_akamai/__init__.py
nornir_akamai/plugins/__init__.py
nornir_akamai/plugins/connections/__init__.py
nornir_akamai/plugins/connections/akamai.py
nornir_akamai/plugins/tasks/__init__.py
nornir_akamai/plugins/tasks/v1/__init__.py
nornir_akamai/plugins/tasks/v1/global_traffic_management.py
nornir_akamai-0.0.1.dist-info/entry_points.txt
nornir_akamai-0.0.1.dist-info/WHEEL
nornir_akamai-0.0.1.dist-info/METADATA
nornir_akamai-0.0.1.dist-info/RECORD
